{
  "project_info": {
    "project_number": "1060094544974",
    "project_id": "chat-app-87b30",
    "storage_bucket": "chat-app-87b30.appspot.com"
  },
  "client": [
    {
      "client_info": {
        "mobilesdk_app_id": "1:1060094544974:android:ced035aff794255448871f",
        "android_client_info": {
          "package_name": "com.example.chat_app"
        }
      },
      "oauth_client": [],
      "api_key": [
        {
          "current_key": "AIzaSyC3LfM1SQtAIMzgEktsEGpiQ0WbWyoRb-Y"
        }
      ],
      "services": {
        "appinvite_service": {
          "other_platform_oauth_client": []
        }
      }
    }
  ],
  "configuration_version": "1"
}